Metadata-Version: 1.0
Name: protect
Version: 2.1.1
Summary: Prediction of T-Cell Epitopes for Cancer Therapy
Home-page: http://github.com/BD2KGenomics/protect
Author: Arjun Arkal Rao
Author-email: aarao@ucsc.edu
License: Apache
Platform: UNKNOWN
